setup.py
src/mongowatch/__init__.py
src/mongowatch/testing.py
src/mongowatch.egg-info/PKG-INFO
src/mongowatch.egg-info/SOURCES.txt
src/mongowatch.egg-info/dependency_links.txt
src/mongowatch.egg-info/not-zip-safe
src/mongowatch.egg-info/requires.txt
src/mongowatch.egg-info/top_level.txt
src/mongowatch/mongo/__init__.py
src/mongowatch/mongo/watcher.py
src/mongowatch/tests/__init__.py
src/mongowatch/tests/test_doc.py
src/mongowatch/tests/test_watcher.py