Metadata-Version: 1.0
Name: mongowatch
Version: 0.1.2dev
Summary: MongoDB traffic pattern watcher
Home-page: UNKNOWN
Author: Russ Ferriday
Author-email: russf@topia.com
License: ZPL 2.1
Keywords: mongo testing
Platform: UNKNOWN
Classifier: Development Status :: 3 - Alpha
Classifier: Intended Audience :: Developers
Classifier: Programming Language :: Python
Classifier: Programming Language :: Python :: 2
Classifier: Framework :: ZODB
Classifier: License :: OSI Approved :: Zope Public License
Classifier: Natural Language :: English
Classifier: Operating System :: OS Independent
